{
  "$schema": "https://ui.shadcn.com/schema/registry-item.json",
  "name": "form",
  "type": "registry:component",
  "title": "Form",
  "description": "表单容器 - 表单容器组件",
  "registryDependencies": [],
  "dependencies": [],
  "files": [
    {
      "path": "blocks/form/form/form.tsx",
      "type": "registry:component",
      "content": "import { FormProvider, useForm, type UseFormPropsExtended } from '@airiot/client'\nimport type { ReactNode } from 'react'\n\ntype FormProps = UseFormPropsExtended & {\n  formId: string\n  children: ReactNode\n  onSubmit: (data: any) => void\n}\n\nconst Form = ({ formId, children, onSubmit, onEffect, ...props } : FormProps ) => {\n  const methods = useForm({ ...props, onEffect })\n  return (\n    <FormProvider {...methods}>\n      <form id={formId} onSubmit={methods.handleSubmit(onSubmit)}>\n        {children}\n      </form>\n    </FormProvider>\n  )\n}\n\nexport default Form"
    }
  ]
}