{
  "name": "view-field-rate",
  "type": "registry:component",
  "title": "View Field Rate",
  "description": "View Field Rate - 组件",
  "dependencies": [
    "lodash"
  ],
  "registryDependencies": [],
  "files": [
    {
      "path": "registry/components/kesi/view-field-rate/view-field-rate.tsx",
      "type": "registry:component",
      "content": "import isNil from 'lodash/isNil'\nimport { cn } from '@/lib/utils'\n\nconst Rate = ({ value, schema }: { value: any; schema?: any }) => {\n  if (isNil(value)) return <span className=\"text-muted-foreground\">空</span>\n  const max = schema?.max || 5\n  return (\n    <div className=\"flex items-center gap-1\">\n      {Array.from({ length: max }).map((_, i) => (\n        <span\n          key={i}\n          className={cn(\n            \"text-lg\",\n            i < value ? \"text-yellow-400\" : \"text-gray-300\"\n          )}\n        >\n          ★\n        </span>\n      ))}\n      <span className=\"ml-2 text-sm text-muted-foreground\">({value})</span>\n    </div>\n  )\n}\n\nexport { Rate }\n"
    }
  ]
}